{
  "schedule": [
    {
      "round": 1,
      "start": 840,
      "end": 846,
      "matches": [
        {
          "court": "A",
          "teamA": "Bykle IL",
          "teamB": "Krossen skole"
        },
        {
          "court": "B",
          "teamA": "Kanonkulene",
          "teamB": "Lova-torden"
        }
      ]
    },
    {
      "round": 1,
      "start": 848,
      "end": 854,
      "matches": [
        {
          "court": "A",
          "teamA": "Lova-lynene",
          "teamB": "Lauvåsen 1"
        },
        {
          "court": "B",
          "teamA": "Randesund Power",
          "teamB": "Lauvåsen 2"
        }
      ]
    },
    {
      "round": 2,
      "start": 857,
      "end": 863,
      "matches": [
        {
          "court": "A",
          "teamA": "Kanonkulene",
          "teamB": "Krossen skole"
        },
        {
          "court": "B",
          "teamA": "Lova-lynene",
          "teamB": "Bykle IL"
        }
      ]
    },
    {
      "round": 2,
      "start": 865,
      "end": 871,
      "matches": [
        {
          "court": "A",
          "teamA": "Lauvåsen 2",
          "teamB": "Lauvåsen 1"
        },
        {
          "court": "B",
          "teamA": "Randesund Power",
          "teamB": "Lova-torden"
        }
      ]
    },
    {
      "round": 3,
      "start": 874,
      "end": 880,
      "matches": [
        {
          "court": "A",
          "teamA": "Kanonkulene",
          "teamB": "Lova-lynene"
        },
        {
          "court": "B",
          "teamA": "Lauvåsen 2",
          "teamB": "Bykle IL"
        }
      ]
    },
    {
      "round": 3,
      "start": 882,
      "end": 888,
      "matches": [
        {
          "court": "A",
          "teamA": "Lova-torden",
          "teamB": "Krossen skole"
        },
        {
          "court": "B",
          "teamA": "Randesund Power",
          "teamB": "Lauvåsen 1"
        }
      ]
    },
    {
      "round": 4,
      "start": 891,
      "end": 897,
      "matches": [
        {
          "court": "A",
          "teamA": "Lauvåsen 1",
          "teamB": "Bykle IL"
        },
        {
          "court": "B",
          "teamA": "Lauvåsen 2",
          "teamB": "Kanonkulene"
        }
      ]
    },
    {
      "round": 4,
      "start": 899,
      "end": 905,
      "matches": [
        {
          "court": "A",
          "teamA": "Lova-torden",
          "teamB": "Lova-lynene"
        },
        {
          "court": "B",
          "teamA": "Randesund Power",
          "teamB": "Krossen skole"
        }
      ]
    },
    {
      "round": 5,
      "start": 908,
      "end": 914,
      "matches": [
        {
          "court": "A",
          "teamA": "Lova-torden",
          "teamB": "Lauvåsen 2"
        },
        {
          "court": "B",
          "teamA": "Lauvåsen 1",
          "teamB": "Kanonkulene"
        }
      ]
    },
    {
      "round": 5,
      "start": 916,
      "end": 922,
      "matches": [
        {
          "court": "A",
          "teamA": "Randesund Power",
          "teamB": "Bykle IL"
        },
        {
          "court": "B",
          "teamA": "Krossen skole",
          "teamB": "Lova-lynene"
        }
      ]
    },
    {
      "round": 6,
      "start": 925,
      "end": 931,
      "matches": [
        {
          "court": "A",
          "teamA": "Bykle IL",
          "teamB": "Kanonkulene"
        },
        {
          "court": "B",
          "teamA": "Lauvåsen 1",
          "teamB": "Lova-torden"
        }
      ]
    },
    {
      "round": 6,
      "start": 933,
      "end": 939,
      "matches": [
        {
          "court": "A",
          "teamA": "Krossen skole",
          "teamB": "Lauvåsen 2"
        },
        {
          "court": "B",
          "teamA": "Randesund Power",
          "teamB": "Lova-lynene"
        }
      ]
    },
    {
      "round": 7,
      "start": 942,
      "end": 948,
      "matches": [
        {
          "court": "A",
          "teamA": "Krossen skole",
          "teamB": "Lauvåsen 1"
        },
        {
          "court": "B",
          "teamA": "Bykle IL",
          "teamB": "Lova-torden"
        }
      ]
    },
    {
      "round": 7,
      "start": 950,
      "end": 956,
      "matches": [
        {
          "court": "A",
          "teamA": "Lova-lynene",
          "teamB": "Lauvåsen 2"
        },
        {
          "court": "B",
          "teamA": "Randesund Power",
          "teamB": "Kanonkulene"
        }
      ]
    }
  ],
  "teams": [
    "Randesund Power",
    "Kanonkulene",
    "Lova-lynene",
    "Bykle IL",
    "Krossen skole",
    "Lauvåsen 1",
    "Lova-torden",
    "Lauvåsen 2"
  ],
  "savedAt": "2026-04-23T20:12:04.851Z",
  "revision": "a4b20facbc4c895d6353d58abb731c99e18b4c7e"
}